<?xml version = '1.0' encoding = 'UTF-8'?>
<Relation class="oracle.dbtools.crest.model.design.logical.Relation" name="Relation_66" directorySegmentName="seg_0" id="5E39A9AF-1BBC-B3E5-F4F7-562711A0D8EA">
<createdBy>sebav</createdBy>
<createdTime>2025-05-11 02:31:32 UTC</createdTime>
<ownerDesignName>ER7</ownerDesignName>
<engineerTo>
<item key="310C8F6A-E6BF-DBE6-9E5B-A1D92908EB34" value="true"/>
</engineerTo>
<sourcePk>17E10DEC-6B73-8C31-BB60-894C143EC8DD</sourcePk>
<arc>D179C3E7-41DE-F124-D04D-64158C3FE69E</arc>
<identifying>false</identifying>
<optionalSource>true</optionalSource>
<optionalTarget>false</optionalTarget>
<sourceCardinality>1</sourceCardinality>
<sourceEntity>B1A10A74-362C-1B21-4301-772CA9313703</sourceEntity>
<targetCardinalityString>*</targetCardinalityString>
<targetEntity>8432D7E4-0FF3-93A8-CE67-769B3677F597</targetEntity>
<transferable>true</transferable>
<deleteRule>NO ACTION</deleteRule>
</Relation>
